{
	"type":"FeatureCollection",
	"totalFeatures":1,
	"features":[
		{
			"type":"Feature",
			"id":"Rupununi 3D",
			"geometry":{
				"type":"Point",
				"coordinates":[-59.4415, 3.4348]
			},
			"geometry_name":"the_geom",
			"properties":{
				"Name":"Rupununi Savanah",
				"mediapath":["hinterland_areas","kanuku","rupununi_panorama"],
				"media_html":"<img width='120px' src='/static/pacmap/data/hinterland_areas/kanuku/rupununi_panorama/negx.png'/>",
				"feature_type":"Launch3D",
				"coordinates":[-59.4415, 3.4348]
			}
		}
	]
}
